<?xml version="1.0" encoding="UTF-8"?>
<!DOCTYPE mapper PUBLIC "-//mybatis.org//DTD Mapper 3.0//EN" "http://mybatis.org/dtd/mybatis-3-mapper.dtd">
<mapper namespace="cn.rongcapital.mkt.dao.dataauth.DataAuthMapper">
  <resultMap id="BaseResultMap" type="cn.rongcapital.mkt.dataauth.po.DataAuth">
    <!--
      WARNING - @mbg.generated
      This element is automatically generated by MyBatis Generator, do not modify.
      This element was generated on Thu Jan 26 22:08:15 CST 2017.
    -->
    <id column="da_id" jdbcType="BIGINT" property="daId" />
    <result column="table_name" jdbcType="VARCHAR" property="tableName" />
    <result column="resource_id" jdbcType="BIGINT" property="resourceId" />
    <result column="org_id" jdbcType="BIGINT" property="orgId" />
    <result column="firsthand" jdbcType="BIT" property="firsthand" />
    <result column="share_type" jdbcType="CHAR" property="shareType" />
    <result column="writeable" jdbcType="BIT" property="writeable" />
    <result column="from_org_id" jdbcType="BIGINT" property="fromOrgId" />
    <result column="from_resource_id" jdbcType="BIGINT" property="fromResourceId" />
    <result column="shared" jdbcType="BIT" property="shared" />
    <result column="share_id" jdbcType="VARCHAR" property="shareId" />
    <result column="create_time" jdbcType="TIMESTAMP" property="createTime" />
    <result column="update_time" jdbcType="TIMESTAMP" property="updateTime" />
  </resultMap>
  <sql id="Base_Column_List">
    <!--
      WARNING - @mbg.generated
      This element is automatically generated by MyBatis Generator, do not modify.
      This element was generated on Thu Jan 26 22:08:15 CST 2017.
    -->
    da_id, `table_name`, resource_id, org_id, firsthand, share_type, writeable, from_org_id, 
    from_resource_id, shared, share_id, create_time, update_time
  </sql>
  <select id="selectByPrimaryKey" parameterType="java.lang.Long" resultMap="BaseResultMap">
    <!--
      WARNING - @mbg.generated
      This element is automatically generated by MyBatis Generator, do not modify.
      This element was generated on Thu Jan 26 22:08:15 CST 2017.
    -->
    select 
    <include refid="Base_Column_List" />
    from data_auth
    where da_id = #{daId,jdbcType=BIGINT}
  </select>
  <delete id="deleteByPrimaryKey" parameterType="java.lang.Long">
    <!--
      WARNING - @mbg.generated
      This element is automatically generated by MyBatis Generator, do not modify.
      This element was generated on Thu Jan 26 22:08:15 CST 2017.
    -->
    delete from data_auth
    where da_id = #{daId,jdbcType=BIGINT}
  </delete>
  <insert id="insert" parameterType="cn.rongcapital.mkt.dataauth.po.DataAuth">
    <!--
      WARNING - @mbg.generated
      This element is automatically generated by MyBatis Generator, do not modify.
      This element was generated on Thu Jan 26 22:08:15 CST 2017.
    -->
    insert into data_auth ( `table_name`, resource_id, 
      org_id, firsthand, share_type, 
      writeable, from_org_id, from_resource_id, 
      shared, share_id, create_time, 
      update_time)
    values ( #{tableName,jdbcType=VARCHAR}, #{resourceId,jdbcType=BIGINT}, 
      #{orgId,jdbcType=BIGINT}, #{firsthand,jdbcType=BIT}, #{shareType,jdbcType=CHAR}, 
      #{writeable,jdbcType=BIT}, #{fromOrgId,jdbcType=BIGINT}, #{fromResourceId,jdbcType=BIGINT}, 
      #{shared,jdbcType=BIT}, #{shareId,jdbcType=VARCHAR}, #{createTime,jdbcType=TIMESTAMP}, 
      #{updateTime,jdbcType=TIMESTAMP})
  </insert>
  <insert id="insertSelective" parameterType="cn.rongcapital.mkt.dataauth.po.DataAuth">
    <!--
      WARNING - @mbg.generated
      This element is automatically generated by MyBatis Generator, do not modify.
      This element was generated on Thu Jan 26 22:08:15 CST 2017.
    -->
    insert into data_auth
    <trim prefix="(" suffix=")" suffixOverrides=",">
      <if test="daId != null">
        da_id,
      </if>
      <if test="tableName != null">
        `table_name`,
      </if>
      <if test="resourceId != null">
        resource_id,
      </if>
      <if test="orgId != null">
        org_id,
      </if>
      <if test="firsthand != null">
        firsthand,
      </if>
      <if test="shareType != null">
        share_type,
      </if>
      <if test="writeable != null">
        writeable,
      </if>
      <if test="fromOrgId != null">
        from_org_id,
      </if>
      <if test="fromResourceId != null">
        from_resource_id,
      </if>
      <if test="shared != null">
        shared,
      </if>
      <if test="shareId != null">
        share_id,
      </if>
      <if test="createTime != null">
        create_time,
      </if>
      <if test="updateTime != null">
        update_time,
      </if>
    </trim>
    <trim prefix="values (" suffix=")" suffixOverrides=",">
      <if test="daId != null">
        #{daId,jdbcType=BIGINT},
      </if>
      <if test="tableName != null">
        #{tableName,jdbcType=VARCHAR},
      </if>
      <if test="resourceId != null">
        #{resourceId,jdbcType=BIGINT},
      </if>
      <if test="orgId != null">
        #{orgId,jdbcType=BIGINT},
      </if>
      <if test="firsthand != null">
        #{firsthand,jdbcType=BIT},
      </if>
      <if test="shareType != null">
        #{shareType,jdbcType=CHAR},
      </if>
      <if test="writeable != null">
        #{writeable,jdbcType=BIT},
      </if>
      <if test="fromOrgId != null">
        #{fromOrgId,jdbcType=BIGINT},
      </if>
      <if test="fromResourceId != null">
        #{fromResourceId,jdbcType=BIGINT},
      </if>
      <if test="shared != null">
        #{shared,jdbcType=BIT},
      </if>
      <if test="shareId != null">
        #{shareId,jdbcType=VARCHAR},
      </if>
      <if test="createTime != null">
        #{createTime,jdbcType=TIMESTAMP},
      </if>
      <if test="updateTime != null">
        #{updateTime,jdbcType=TIMESTAMP},
      </if>
    </trim>
  </insert>
  <update id="updateByPrimaryKeySelective" parameterType="cn.rongcapital.mkt.dataauth.po.DataAuth">
    <!--
      WARNING - @mbg.generated
      This element is automatically generated by MyBatis Generator, do not modify.
      This element was generated on Thu Jan 26 22:08:15 CST 2017.
    -->
    update data_auth
    <set>
      <if test="tableName != null">
        `table_name` = #{tableName,jdbcType=VARCHAR},
      </if>
      <if test="resourceId != null">
        resource_id = #{resourceId,jdbcType=BIGINT},
      </if>
      <if test="orgId != null">
        org_id = #{orgId,jdbcType=BIGINT},
      </if>
      <if test="firsthand != null">
        firsthand = #{firsthand,jdbcType=BIT},
      </if>
      <if test="shareType != null">
        share_type = #{shareType,jdbcType=CHAR},
      </if>
      <if test="writeable != null">
        writeable = #{writeable,jdbcType=BIT},
      </if>
      <if test="fromOrgId != null">
        from_org_id = #{fromOrgId,jdbcType=BIGINT},
      </if>
      <if test="fromResourceId != null">
        from_resource_id = #{fromResourceId,jdbcType=BIGINT},
      </if>
      <if test="shared != null">
        shared = #{shared,jdbcType=BIT},
      </if>
      <if test="shareId != null">
        share_id = #{shareId,jdbcType=VARCHAR},
      </if>
      <if test="createTime != null">
        create_time = #{createTime,jdbcType=TIMESTAMP},
      </if>
      <if test="updateTime != null">
        update_time = #{updateTime,jdbcType=TIMESTAMP},
      </if>
    </set>
    where da_id = #{daId,jdbcType=BIGINT}
  </update>
  <update id="updateByPrimaryKey" parameterType="cn.rongcapital.mkt.dataauth.po.DataAuth">
    <!--
      WARNING - @mbg.generated
      This element is automatically generated by MyBatis Generator, do not modify.
      This element was generated on Thu Jan 26 22:08:15 CST 2017.
    -->
    update data_auth
    set `table_name` = #{tableName,jdbcType=VARCHAR},
      resource_id = #{resourceId,jdbcType=BIGINT},
      org_id = #{orgId,jdbcType=BIGINT},
      firsthand = #{firsthand,jdbcType=BIT},
      share_type = #{shareType,jdbcType=CHAR},
      writeable = #{writeable,jdbcType=BIT},
      from_org_id = #{fromOrgId,jdbcType=BIGINT},
      from_resource_id = #{fromResourceId,jdbcType=BIGINT},
      shared = #{shared,jdbcType=BIT},
      share_id = #{shareId,jdbcType=VARCHAR},
      create_time = #{createTime,jdbcType=TIMESTAMP},
      update_time = #{updateTime,jdbcType=TIMESTAMP}
    where da_id = #{daId,jdbcType=BIGINT}
  </update>
  
  <delete id="deleteDataAuth" parameterType="cn.rongcapital.mkt.dataauth.po.DataAuth">
	<![CDATA[    
		delete from data_auth 
    	where table_Name = #{tableName} and resource_Id = #{resourceId}
    ]]>
	</delete>
	
	<select id="selectByPrimaryKeyAndLevelOwner" parameterType="hashMap" resultMap="BaseResultMap">
    <!--
      WARNING - @mbg.generated
      This element is automatically generated by MyBatis Generator, do not modify.
      This element was generated on Sun Jan 22 08:56:41 CST 2017.
    -->
    select 
    <include refid="Base_Column_List" />
    from data_auth
    where 
    table_name=#{tableName}
    and resource_id=#{resourceId}
    and org_id=#{orgId}
    and share_type is null
  </select>
  
  <select id="selectByOwnerAndShare" parameterType="hashMap" resultMap="BaseResultMap">
    <!--
      WARNING - @mbg.generated
      This element is automatically generated by MyBatis Generator, do not modify.
      This element was generated on Sun Jan 22 08:56:41 CST 2017.
    -->
    select 
    <include refid="Base_Column_List" />
    from data_auth
    where 
    table_name=#{tableName}
    and resource_id=#{resourceId}
    and org_id=#{orgId}
    and share_type = 'S'
  </select>
  
    <select id="selectByTableNameResourceIDOrgId" parameterType="hashMap" resultMap="BaseResultMap">
    select 
    <include refid="Base_Column_List" />
    from data_auth
    where 
    table_name=#{tableName}
    and resource_id=#{resourceId}
    and org_id=#{orgId}
  </select>
  
  
  
  <select id="selectByRidAndOrgId" parameterType="hashMap" resultMap="BaseResultMap">
    select 
    <include refid="Base_Column_List" />
    from data_access
    where 
    	table_name=#{tableName}
    	and resource_id = #{resourceId}
    	and org_id = #{orgId}
  </select>
  
  <select id="selectByShareId" parameterType="string" resultMap="BaseResultMap">
    
    select 
    <include refid="Base_Column_List" />
    from data_auth
    where 
    	firsthand=1
    	and share_id = #{shareId}
  </select>
  
  <select id="selectByOrgIds" resultMap="BaseResultMap">
    select 
    <include refid="Base_Column_List" />
    from data_auth
    where 
    	table_name = #{tableName}
    	and resource_id = #{resourceId}
    	and org_id in
    	<foreach collection="list" item="orgId" index="index"
            open="(" close=")" separator=",">
            #{orgId}
        </foreach>
  </select>
  
  <select id="selectByFromOrgIds" parameterType="map" resultMap="BaseResultMap">
    select 
    <include refid="Base_Column_List" />
    from data_auth
    where 
    table_name=#{tableName}
    and from_resource_id=#{fromResourceId}
    and from_org_id=#{fromOrgId}
  </select>
  
  
</mapper>